tot_plus/__init__.py
tot_plus/plus.py
tot_plus-0.2.3.dist-info/METADATA
tot_plus-0.2.3.dist-info/WHEEL
tot_plus-0.2.3.dist-info/entry_points.txt
tot_plus-0.2.3.dist-info/top_level.txt
tot_plus-0.2.3.dist-info/RECORD
