Metadata-Version: 2.1
Name: tot_plus
Version: 0.2.3
Summary: Default template for PDM package
Author-email: EstherCho-7 <dkgkqm777@gmail.com>
License: MIT
Requires-Python: >=3.9
